README
setup.py
mwapi/__init__.py
python_mwapi.egg-info/PKG-INFO
python_mwapi.egg-info/SOURCES.txt
python_mwapi.egg-info/dependency_links.txt
python_mwapi.egg-info/requires.txt
python_mwapi.egg-info/top_level.txt