Metadata-Version: 1.0
Name: python-mwapi
Version: 0.1.1
Summary: Simple wrapper for the Mediawiki API
Home-page: http://github.com/yuvipanda/python-mwapi
Author: Yuvi Panda
Author-email: yuvipanda@gmail.com
License: MIT License
Platform: UNKNOWN
